finch/__init__.py
finch/_base_client.py
finch/_client.py
finch/_compat.py
finch/_constants.py
finch/_exceptions.py
finch/_files.py
finch/_legacy_response.py
finch/_models.py
finch/_qs.py
finch/_resource.py
finch/_response.py
finch/_streaming.py
finch/_types.py
finch/_version.py
finch/pagination.py
finch/py.typed
finch/_utils/__init__.py
finch/_utils/_compat.py
finch/_utils/_datetime_parse.py
finch/_utils/_logs.py
finch/_utils/_proxy.py
finch/_utils/_reflection.py
finch/_utils/_resources_proxy.py
finch/_utils/_streams.py
finch/_utils/_sync.py
finch/_utils/_transform.py
finch/_utils/_typing.py
finch/_utils/_utils.py
finch/lib/.keep
finch/resources/__init__.py
finch/resources/access_tokens.py
finch/resources/account.py
finch/resources/providers.py
finch/resources/request_forwarding.py
finch/resources/webhooks.py
finch/resources/connect/__init__.py
finch/resources/connect/connect.py
finch/resources/connect/sessions.py
finch/resources/hris/__init__.py
finch/resources/hris/directory.py
finch/resources/hris/documents.py
finch/resources/hris/employments.py
finch/resources/hris/hris.py
finch/resources/hris/individuals.py
finch/resources/hris/pay_statements.py
finch/resources/hris/payments.py
finch/resources/hris/benefits/__init__.py
finch/resources/hris/benefits/benefits.py
finch/resources/hris/benefits/individuals.py
finch/resources/hris/company/__init__.py
finch/resources/hris/company/company.py
finch/resources/hris/company/pay_statement_item/__init__.py
finch/resources/hris/company/pay_statement_item/pay_statement_item.py
finch/resources/hris/company/pay_statement_item/rules.py
finch/resources/jobs/__init__.py
finch/resources/jobs/automated.py
finch/resources/jobs/jobs.py
finch/resources/jobs/manual.py
finch/resources/payroll/__init__.py
finch/resources/payroll/pay_groups.py
finch/resources/payroll/payroll.py
finch/resources/sandbox/__init__.py
finch/resources/sandbox/company.py
finch/resources/sandbox/directory.py
finch/resources/sandbox/employment.py
finch_api-1.43.0.dist-info/METADATA
finch_api-1.43.0.dist-info/WHEEL
finch_api-1.43.0.dist-info/licenses/LICENSE
finch_api-1.43.0.dist-info/RECORD
